<!--
  gThumb

  Copyright © 2011 Free Software Foundation, Inc.

  This program is free software; you can redistribute it and/or modify
  it under the terms of the GNU General Public License as published by
  the Free Software Foundation; either version 2 of the License, or
  (at your option) any later version.

  This program is distributed in the hope that it will be useful,
  but WITHOUT ANY WARRANTY; without even the implied warranty of
  MERCHANTABILITY or FITNESS FOR A PARTICULAR PURPOSE.  See the
  GNU General Public License for more details.

  You should have received a copy of the GNU General Public License
  along with this program.  If not, see <http://www.gnu.org/licenses/>.
-->
<schemalist>

  <schema id="org.gnome.gthumb.resize" path="/org/gnome/gthumb/resize/" gettext-domain="gthumb">
    <key name="unit" enum="org.gnome.gthumb.GthUnit">
      <default>'percentage'</default>
    </key>
    <key name="width" type="d">
      <default>100.0</default>
    </key>
    <key name="height" type="d">
      <default>100.0</default>
    </key>
    <key name="aspect-ratio-width" type="i">
      <default>1</default>
    </key>
    <key name="aspect-ratio-height" type="i">
      <default>1</default>
    </key>
    <key name="aspect-ratio" enum="org.gnome.gthumb.GthAspectRatio">
      <default>'image'</default>
    </key>
    <key name="aspect-ratio-invert" type="b">
      <default>true</default>
    </key>
    <key name="high-quality" type="b">
      <default>true</default>
    </key>
  </schema>

</schemalist>
